<?xml version="1.0"?>
<exportedFiles>
  <exportedFile url="\Portal\SlxMobile\SourceFiles\argos-SDK\libraries\dojo\dojox\encoding\digests\MD5.js" timeStamp="2013-12-27T17:57:52.0000" />
  <exportedFile url="\Portal\SlxMobile\SourceFiles\argos-SDK\libraries\dojo\dojox\encoding\digests\MD5.js.uncompressed.js" timeStamp="2013-12-27T17:57:52.0000" />
  <exportedFile url="\Portal\SlxMobile\SourceFiles\argos-SDK\libraries\dojo\dojox\encoding\digests\SHA1.js" timeStamp="2013-12-27T17:57:52.0000" />
  <exportedFile url="\Portal\SlxMobile\SourceFiles\argos-SDK\libraries\dojo\dojox\encoding\digests\SHA1.js.uncompressed.js" timeStamp="2013-12-27T17:57:52.0000" />
  <exportedFile url="\Portal\SlxMobile\SourceFiles\argos-SDK\libraries\dojo\dojox\encoding\digests\SHA224.js" timeStamp="2013-12-27T17:57:52.0000" />
  <exportedFile url="\Portal\SlxMobile\SourceFiles\argos-SDK\libraries\dojo\dojox\encoding\digests\SHA224.js.uncompressed.js" timeStamp="2013-12-27T17:57:52.0000" />
  <exportedFile url="\Portal\SlxMobile\SourceFiles\argos-SDK\libraries\dojo\dojox\encoding\digests\SHA256.js" timeStamp="2013-12-27T17:57:52.0000" />
  <exportedFile url="\Portal\SlxMobile\SourceFiles\argos-SDK\libraries\dojo\dojox\encoding\digests\SHA256.js.uncompressed.js" timeStamp="2013-12-27T17:57:52.0000" />
  <exportedFile url="\Portal\SlxMobile\SourceFiles\argos-SDK\libraries\dojo\dojox\encoding\digests\SHA384.js" timeStamp="2013-12-27T17:57:52.0000" />
  <exportedFile url="\Portal\SlxMobile\SourceFiles\argos-SDK\libraries\dojo\dojox\encoding\digests\SHA384.js.uncompressed.js" timeStamp="2013-12-27T17:57:52.0000" />
  <exportedFile url="\Portal\SlxMobile\SourceFiles\argos-SDK\libraries\dojo\dojox\encoding\digests\SHA512.js" timeStamp="2013-12-27T17:57:52.0000" />
  <exportedFile url="\Portal\SlxMobile\SourceFiles\argos-SDK\libraries\dojo\dojox\encoding\digests\SHA512.js.uncompressed.js" timeStamp="2013-12-27T17:57:52.0000" />
  <exportedFile url="\Portal\SlxMobile\SourceFiles\argos-SDK\libraries\dojo\dojox\encoding\digests\_base.js" timeStamp="2013-12-27T17:57:52.0000" />
  <exportedFile url="\Portal\SlxMobile\SourceFiles\argos-SDK\libraries\dojo\dojox\encoding\digests\_base.js.uncompressed.js" timeStamp="2013-12-27T17:57:52.0000" />
  <exportedFile url="\Portal\SlxMobile\SourceFiles\argos-SDK\libraries\dojo\dojox\encoding\digests\_sha-32.js" timeStamp="2013-12-27T17:57:52.0000" />
  <exportedFile url="\Portal\SlxMobile\SourceFiles\argos-SDK\libraries\dojo\dojox\encoding\digests\_sha-32.js.uncompressed.js" timeStamp="2013-12-27T17:57:52.0000" />
  <exportedFile url="\Portal\SlxMobile\SourceFiles\argos-SDK\libraries\dojo\dojox\encoding\digests\_sha-64.js" timeStamp="2013-12-27T17:57:52.0000" />
  <exportedFile url="\Portal\SlxMobile\SourceFiles\argos-SDK\libraries\dojo\dojox\encoding\digests\_sha-64.js.uncompressed.js" timeStamp="2013-12-27T17:57:52.0000" />
</exportedFiles>