<?xml version="1.0"?>
<exportedFiles>
  <exportedFile url="\deployment\webroot\common\SmartParts\SyncJob\App_LocalResources\LogItems.ascx.de.resx" timeStamp="2014-11-27T14:28:46.0000" />
  <exportedFile url="\deployment\webroot\common\SmartParts\SyncJob\App_LocalResources\LogItems.ascx.fr.resx" timeStamp="2014-11-27T14:28:46.0000" />
  <exportedFile url="\deployment\webroot\common\SmartParts\SyncJob\App_LocalResources\LogItems.ascx.it.resx" timeStamp="2014-11-27T14:28:46.0000" />
  <exportedFile url="\deployment\webroot\common\SmartParts\SyncJob\App_LocalResources\LogItems.ascx.resx" timeStamp="2014-11-27T14:28:46.0000" />
  <exportedFile url="\deployment\webroot\common\SmartParts\SyncJob\App_LocalResources\LogItems.ascx.ru.resx" timeStamp="2014-11-27T14:28:46.0000" />
  <exportedFile url="\deployment\webroot\common\SmartParts\SyncJob\App_LocalResources\SyncHistory.ascx.de.resx" timeStamp="2014-11-27T14:28:48.0000" />
  <exportedFile url="\deployment\webroot\common\SmartParts\SyncJob\App_LocalResources\SyncHistory.ascx.fr.resx" timeStamp="2014-11-27T14:28:48.0000" />
  <exportedFile url="\deployment\webroot\common\SmartParts\SyncJob\App_LocalResources\SyncHistory.ascx.it.resx" timeStamp="2014-11-27T14:28:48.0000" />
  <exportedFile url="\deployment\webroot\common\SmartParts\SyncJob\App_LocalResources\SyncHistory.ascx.resx" timeStamp="2014-11-27T14:28:48.0000" />
  <exportedFile url="\deployment\webroot\common\SmartParts\SyncJob\App_LocalResources\SyncHistory.ascx.ru.resx" timeStamp="2014-11-27T14:28:48.0000" />
  <exportedFile url="\deployment\webroot\common\SmartParts\SyncJob\App_LocalResources\SyncJobDetails.ascx.de.resx" timeStamp="2014-11-27T14:28:48.0000" />
  <exportedFile url="\deployment\webroot\common\SmartParts\SyncJob\App_LocalResources\SyncJobDetails.ascx.fr.resx" timeStamp="2014-11-27T14:28:48.0000" />
  <exportedFile url="\deployment\webroot\common\SmartParts\SyncJob\App_LocalResources\SyncJobDetails.ascx.it.resx" timeStamp="2014-11-27T14:28:48.0000" />
  <exportedFile url="\deployment\webroot\common\SmartParts\SyncJob\App_LocalResources\SyncJobDetails.ascx.resx" timeStamp="2014-11-27T14:28:48.0000" />
  <exportedFile url="\deployment\webroot\common\SmartParts\SyncJob\App_LocalResources\SyncJobDetails.ascx.ru.resx" timeStamp="2014-11-27T14:28:48.0000" />
</exportedFiles>