<?xml version="1.0"?>
<exportedFiles>
  <exportedFile url="\Portal\SlxClient\ChildPages\JoinEditor\JoinEditor.page.xml" timeStamp="2014-01-07T23:59:13.0000" />
  <exportedFile url="\Portal\SlxClient\ChildPages\JoinEditor\JoinEditor.page.xml.de.resx" timeStamp="2014-01-07T23:59:13.0000" />
  <exportedFile url="\Portal\SlxClient\ChildPages\JoinEditor\JoinEditor.page.xml.fr.resx" timeStamp="2014-01-07T23:59:13.0000" />
  <exportedFile url="\Portal\SlxClient\ChildPages\JoinEditor\JoinEditor.page.xml.it.resx" timeStamp="2014-01-07T23:59:13.0000" />
  <exportedFile url="\Portal\SlxClient\ChildPages\JoinEditor\JoinEditor.page.xml.resx" timeStamp="2014-01-07T23:59:13.0000" />
  <exportedFile url="\Portal\SlxClient\ChildPages\JoinEditor\JoinEditor.page.xml.ru.resx" timeStamp="2014-01-07T23:59:13.0000" />
  <exportedFile url="\Portal\SlxClient\ChildPages\JoinEditor\SmartParts.order.xml" timeStamp="2014-01-07T23:59:13.0000" />
  <exportedFile url="\Portal\SlxClient\ChildPages\JoinEditor\SmartParts\" />
</exportedFiles>