<?xml version="1.0"?>
<exportedFiles>
  <exportedFile url="\Portal\SlxMobile\SourceFiles\argos-SDK\libraries\dojo\dojox\editor\plugins\nls\ar\AutoSave.js" timeStamp="2013-12-27T17:57:49.0000" />
  <exportedFile url="\Portal\SlxMobile\SourceFiles\argos-SDK\libraries\dojo\dojox\editor\plugins\nls\ar\AutoSave.js.uncompressed.js" timeStamp="2013-12-27T17:57:49.0000" />
  <exportedFile url="\Portal\SlxMobile\SourceFiles\argos-SDK\libraries\dojo\dojox\editor\plugins\nls\ar\Blockquote.js" timeStamp="2013-12-27T17:57:49.0000" />
  <exportedFile url="\Portal\SlxMobile\SourceFiles\argos-SDK\libraries\dojo\dojox\editor\plugins\nls\ar\Blockquote.js.uncompressed.js" timeStamp="2013-12-27T17:57:49.0000" />
  <exportedFile url="\Portal\SlxMobile\SourceFiles\argos-SDK\libraries\dojo\dojox\editor\plugins\nls\ar\Breadcrumb.js" timeStamp="2013-12-27T17:57:49.0000" />
  <exportedFile url="\Portal\SlxMobile\SourceFiles\argos-SDK\libraries\dojo\dojox\editor\plugins\nls\ar\Breadcrumb.js.uncompressed.js" timeStamp="2013-12-27T17:57:49.0000" />
  <exportedFile url="\Portal\SlxMobile\SourceFiles\argos-SDK\libraries\dojo\dojox\editor\plugins\nls\ar\CollapsibleToolbar.js" timeStamp="2013-12-27T17:57:49.0000" />
  <exportedFile url="\Portal\SlxMobile\SourceFiles\argos-SDK\libraries\dojo\dojox\editor\plugins\nls\ar\CollapsibleToolbar.js.uncompressed.js" timeStamp="2013-12-27T17:57:49.0000" />
  <exportedFile url="\Portal\SlxMobile\SourceFiles\argos-SDK\libraries\dojo\dojox\editor\plugins\nls\ar\FindReplace.js" timeStamp="2013-12-27T17:57:49.0000" />
  <exportedFile url="\Portal\SlxMobile\SourceFiles\argos-SDK\libraries\dojo\dojox\editor\plugins\nls\ar\FindReplace.js.uncompressed.js" timeStamp="2013-12-27T17:57:49.0000" />
  <exportedFile url="\Portal\SlxMobile\SourceFiles\argos-SDK\libraries\dojo\dojox\editor\plugins\nls\ar\InsertAnchor.js" timeStamp="2013-12-27T17:57:49.0000" />
  <exportedFile url="\Portal\SlxMobile\SourceFiles\argos-SDK\libraries\dojo\dojox\editor\plugins\nls\ar\InsertAnchor.js.uncompressed.js" timeStamp="2013-12-27T17:57:49.0000" />
  <exportedFile url="\Portal\SlxMobile\SourceFiles\argos-SDK\libraries\dojo\dojox\editor\plugins\nls\ar\InsertEntity.js" timeStamp="2013-12-27T17:57:49.0000" />
  <exportedFile url="\Portal\SlxMobile\SourceFiles\argos-SDK\libraries\dojo\dojox\editor\plugins\nls\ar\InsertEntity.js.uncompressed.js" timeStamp="2013-12-27T17:57:49.0000" />
  <exportedFile url="\Portal\SlxMobile\SourceFiles\argos-SDK\libraries\dojo\dojox\editor\plugins\nls\ar\latinEntities.js" timeStamp="2013-12-27T17:57:49.0000" />
  <exportedFile url="\Portal\SlxMobile\SourceFiles\argos-SDK\libraries\dojo\dojox\editor\plugins\nls\ar\latinEntities.js.uncompressed.js" timeStamp="2013-12-27T17:57:49.0000" />
  <exportedFile url="\Portal\SlxMobile\SourceFiles\argos-SDK\libraries\dojo\dojox\editor\plugins\nls\ar\LocalImage.js" timeStamp="2013-12-27T17:57:49.0000" />
  <exportedFile url="\Portal\SlxMobile\SourceFiles\argos-SDK\libraries\dojo\dojox\editor\plugins\nls\ar\LocalImage.js.uncompressed.js" timeStamp="2013-12-27T17:57:49.0000" />
  <exportedFile url="\Portal\SlxMobile\SourceFiles\argos-SDK\libraries\dojo\dojox\editor\plugins\nls\ar\PageBreak.js" timeStamp="2013-12-27T17:57:49.0000" />
  <exportedFile url="\Portal\SlxMobile\SourceFiles\argos-SDK\libraries\dojo\dojox\editor\plugins\nls\ar\PageBreak.js.uncompressed.js" timeStamp="2013-12-27T17:57:49.0000" />
  <exportedFile url="\Portal\SlxMobile\SourceFiles\argos-SDK\libraries\dojo\dojox\editor\plugins\nls\ar\PasteFromWord.js" timeStamp="2013-12-27T17:57:49.0000" />
  <exportedFile url="\Portal\SlxMobile\SourceFiles\argos-SDK\libraries\dojo\dojox\editor\plugins\nls\ar\PasteFromWord.js.uncompressed.js" timeStamp="2013-12-27T17:57:49.0000" />
  <exportedFile url="\Portal\SlxMobile\SourceFiles\argos-SDK\libraries\dojo\dojox\editor\plugins\nls\ar\Preview.js" timeStamp="2013-12-27T17:57:49.0000" />
  <exportedFile url="\Portal\SlxMobile\SourceFiles\argos-SDK\libraries\dojo\dojox\editor\plugins\nls\ar\Preview.js.uncompressed.js" timeStamp="2013-12-27T17:57:49.0000" />
  <exportedFile url="\Portal\SlxMobile\SourceFiles\argos-SDK\libraries\dojo\dojox\editor\plugins\nls\ar\SafePaste.js" timeStamp="2013-12-27T17:57:49.0000" />
  <exportedFile url="\Portal\SlxMobile\SourceFiles\argos-SDK\libraries\dojo\dojox\editor\plugins\nls\ar\SafePaste.js.uncompressed.js" timeStamp="2013-12-27T17:57:49.0000" />
  <exportedFile url="\Portal\SlxMobile\SourceFiles\argos-SDK\libraries\dojo\dojox\editor\plugins\nls\ar\Save.js" timeStamp="2013-12-27T17:57:49.0000" />
  <exportedFile url="\Portal\SlxMobile\SourceFiles\argos-SDK\libraries\dojo\dojox\editor\plugins\nls\ar\Save.js.uncompressed.js" timeStamp="2013-12-27T17:57:49.0000" />
  <exportedFile url="\Portal\SlxMobile\SourceFiles\argos-SDK\libraries\dojo\dojox\editor\plugins\nls\ar\ShowBlockNodes.js" timeStamp="2013-12-27T17:57:49.0000" />
  <exportedFile url="\Portal\SlxMobile\SourceFiles\argos-SDK\libraries\dojo\dojox\editor\plugins\nls\ar\ShowBlockNodes.js.uncompressed.js" timeStamp="2013-12-27T17:57:49.0000" />
  <exportedFile url="\Portal\SlxMobile\SourceFiles\argos-SDK\libraries\dojo\dojox\editor\plugins\nls\ar\Smiley.js" timeStamp="2013-12-27T17:57:49.0000" />
  <exportedFile url="\Portal\SlxMobile\SourceFiles\argos-SDK\libraries\dojo\dojox\editor\plugins\nls\ar\Smiley.js.uncompressed.js" timeStamp="2013-12-27T17:57:49.0000" />
  <exportedFile url="\Portal\SlxMobile\SourceFiles\argos-SDK\libraries\dojo\dojox\editor\plugins\nls\ar\SpellCheck.js" timeStamp="2013-12-27T17:57:49.0000" />
  <exportedFile url="\Portal\SlxMobile\SourceFiles\argos-SDK\libraries\dojo\dojox\editor\plugins\nls\ar\SpellCheck.js.uncompressed.js" timeStamp="2013-12-27T17:57:49.0000" />
  <exportedFile url="\Portal\SlxMobile\SourceFiles\argos-SDK\libraries\dojo\dojox\editor\plugins\nls\ar\TableDialog.js" timeStamp="2013-12-27T17:57:49.0000" />
  <exportedFile url="\Portal\SlxMobile\SourceFiles\argos-SDK\libraries\dojo\dojox\editor\plugins\nls\ar\TableDialog.js.uncompressed.js" timeStamp="2013-12-27T17:57:49.0000" />
  <exportedFile url="\Portal\SlxMobile\SourceFiles\argos-SDK\libraries\dojo\dojox\editor\plugins\nls\ar\TextColor.js" timeStamp="2013-12-27T17:57:49.0000" />
  <exportedFile url="\Portal\SlxMobile\SourceFiles\argos-SDK\libraries\dojo\dojox\editor\plugins\nls\ar\TextColor.js.uncompressed.js" timeStamp="2013-12-27T17:57:49.0000" />
</exportedFiles>